{
  "project_info": {
    "project_number": "1093308422320",
    "firebase_url": "https://ubiquitous-lab-assistant.firebaseio.com",
    "project_id": "ubiquitous-lab-assistant",
    "storage_bucket": "ubiquitous-lab-assistant.appspot.com"
  },
  "client": [
    {
      "client_info": {
        "mobilesdk_app_id": "1:1093308422320:android:c8f380c020af612f",
        "android_client_info": {
          "package_name": "com.example.android.ubiquitouslabassistantsystem"
        }
      },
      "oauth_client": [
        {
          "client_id": "1093308422320-8vta73s4tu3c2uo062cu409798anub4t.apps.googleusercontent.com",
          "client_type": 3
        }
      ],
      "api_key": [
        {
          "current_key": "AIzaSyD2WYCSGU6r8L-jEf37pQRdbA80Qp3w43c"
        }
      ],
      "services": {
        "analytics_service": {
          "status": 1
        },
        "appinvite_service": {
          "status": 1,
          "other_platform_oauth_client": []
        },
        "ads_service": {
          "status": 2
        }
      }
    }
  ],
  "configuration_version": "1"
}